aksarantara/Map.py
aksarantara/Ranjana.py
aksarantara/convert.py
aksarantara/data.json
aksarantara/data.py
aksarantara/data.yaml
aksarantara/doc.py
aksarantara/fixer.py
aksarantara/post_options.py
aksarantara/post_processing.py
aksarantara/pre_options.py
aksarantara/pre_processing.py
aksarantara/trans.py
aksarantara/transliterate.py
Aksarantara-1.1.0.dist-info/LICENSE
Aksarantara-1.1.0.dist-info/METADATA
Aksarantara-1.1.0.dist-info/WHEEL
Aksarantara-1.1.0.dist-info/top_level.txt
Aksarantara-1.1.0.dist-info/RECORD
