Metadata-Version: 2.1
Name: Aksarantara
Version: 1.1.0
Summary: Transliteration framework for Indic language mainly focusing on Sanskrit
Home-page: https://github.com/enginestein/Aksarantara
Author: Arya Praneil Pritesh
Author-email: aryapraneil@gmail.com
License: GNU GPL 3.0
Classifier: Programming Language :: Python :: 3
Classifier: Operating System :: OS Independent
Requires-Python: >=3.6
License-File: LICENSE
Requires-Dist: Requests (>=2.20.1)
Requires-Dist: pykakasi (>=2.0.6)
Requires-Dist: pyyaml (>=5.4.1)
Requires-Dist: langcodes (>=3.1.0)
Requires-Dist: language-data
Requires-Dist: regex (>=2021.8.3)
Requires-Dist: fonttools[unicode] (>=4.27)
Requires-Dist: lxml
